{
    "format_version": "1.12", 
    "minecraft:recipe_shaped": {
        "description": {
            "identifier": "xxxooxxoo"
        }, 
        "key": {
            "O": {
                "item": "minecraft:wooden_hoe"
            }, 
            "X": {
                "item": "minecraft:bow"
            }
        }, 
        "pattern": [
            "XXX", 
            "OOX", 
            "XOO"
        ], 
        "result": {
            "item": "minecraft:diamond"
        }, 
        "tags": [
            "crafting_table"
        ]
    }
}