{
    "format_version": "1.12", 
    "minecraft:recipe_shaped": {
        "description": {
            "identifier": "xxxo__oo_"
        }, 
        "key": {
            "O": {
                "item": "minecraft:wooden_hoe"
            }, 
            "X": {
                "item": "minecraft:bow"
            }
        }, 
        "pattern": [
            "XXX", 
            "O  ", 
            "OO "
        ], 
        "result": {
            "item": "minecraft:diamond"
        }, 
        "tags": [
            "crafting_table"
        ]
    }
}